README.md
setup.py
transfer_learning/__init__.py
transfer_learning/celery.py
transfer_learning/database.py
transfer_learning/image.py
transfer_learning/tl_logging.py
transfer_learning/utils.py
transfer_learning.egg-info/PKG-INFO
transfer_learning.egg-info/SOURCES.txt
transfer_learning.egg-info/dependency_links.txt
transfer_learning.egg-info/not-zip-safe
transfer_learning.egg-info/requires.txt
transfer_learning.egg-info/top_level.txt
transfer_learning/cutout/__init__.py
transfer_learning/cutout/cutout.py
transfer_learning/cutout/generators.py
transfer_learning/data/__init__.py
transfer_learning/data/data.py
transfer_learning/fingerprint/__init__.py
transfer_learning/fingerprint/fingerprint.py
transfer_learning/fingerprint/processing.py
transfer_learning/fingerprint/task.py
transfer_learning/misc/__init__.py
transfer_learning/misc/image_processing.py
transfer_learning/similarity/__init__.py
transfer_learning/similarity/display.py
transfer_learning/similarity/qtdisplay.py
transfer_learning/similarity/similarity.py
transfer_learning/similarity/task.py