Metadata-Version: 1.2
Name: transfer-learning
Version: 0.2
Summary: Transfer learning info.
Home-page: https://github.com/brechmos-stsci/transfer-learning
Author: Craig Jones
Author-email: craig@brechmos.org
License: GPLV3.0
Keywords: detect,open,file,handle,psutil,pytest,py.test
Platform: UNKNOWN
Classifier: Development Status :: 3 - Alpha
Classifier: Framework :: Pytest
Classifier: Intended Audience :: Developers
Classifier: License :: OSI Approved :: BSD License
Classifier: Operating System :: OS Independent
Classifier: Programming Language :: Python
Classifier: Programming Language :: Python :: 3
Classifier: Programming Language :: Python :: 3.5
Classifier: Programming Language :: Python :: 3.6
Classifier: Programming Language :: Python :: Implementation :: CPython
Classifier: Topic :: Software Development :: Testing
Classifier: Topic :: Utilities
Requires-Python: >=3.5
